<?xml version="1.0" encoding="utf-8" ?><dwsync><file name="buttonsmall_clear.gif" server="wsa123.uits.indiana.edu//usr/local/apache/htdocs/mocks/" local="3280776268" remote="2729553974472726699" /><file name="buttonsmall_search.gif" server="wsa123.uits.indiana.edu//usr/local/apache/htdocs/mocks/" local="3280776268" remote="2729553974472726699" /><file name="en-common.js" server="wsa123.uits.indiana.edu//usr/local/apache/htdocs/mocks/" local="3280776268" remote="2729553974472726699" /><file name="lookupable-common.js" server="wsa123.uits.indiana.edu//usr/local/apache/htdocs/mocks/" local="3280776268" remote="2729553974472726699" /><file name="pixel_clear.gif" server="wsa123.uits.indiana.edu//usr/local/apache/htdocs/mocks/" local="3280776268" remote="2729553974472726699" /><file name="screen.css" server="wsa123.uits.indiana.edu//usr/local/apache/htdocs/mocks/" local="3280776268" remote="2729548047417858218" /><file name="searchicon.gif" server="wsa123.uits.indiana.edu//usr/local/apache/htdocs/mocks/" local="3280776268" remote="2729553974472726699" /><file name="wf-logo.gif" server="wsa123.uits.indiana.edu//usr/local/apache/htdocs/mocks/" local="3280776268" remote="2729553974472726699" /></dwsync>