<?xml version="1.0" encoding="utf-8" ?><dwsync><file name="bc-doc.html" server="wsa123.uits.indiana.edu//usr/local/apache/htdocs/mocks/" local="3288867252" remote="2014837383102996921" /><file name="salarysetting.html" server="wsa123.uits.indiana.edu//usr/local/apache/htdocs/mocks/" local="3289987527" remote="1971393170429786567" /><file name="salarysetting-pos2.html" server="wsa123.uits.indiana.edu//usr/local/apache/htdocs/mocks/" local="3289924277" remote="2884731056984441525" /><file name="salarysetting-inc2.html" server="wsa123.uits.indiana.edu//usr/local/apache/htdocs/mocks/" local="3289922792" remote="2387936502003285224" /><file name="salarysetting-inc1.html" server="wsa123.uits.indiana.edu//usr/local/apache/htdocs/mocks/" local="3289922769" remote="2711869635616586961" /><file name="salarysetting-pos1.html" server="wsa123.uits.indiana.edu//usr/local/apache/htdocs/mocks/" local="3289923979" remote="1979406857849553291" /><file name="salarysetting-inc.html" server="wsa123.uits.indiana.edu//usr/local/apache/htdocs/mocks/" local="3289986396" remote="2377544175795647835" /><file name="salarysetting-pos.html" server="wsa123.uits.indiana.edu//usr/local/apache/htdocs/mocks/" local="3289987016" remote="2794280231141717960" /></dwsync>