<?xml version="1.0" encoding="utf-8" ?><dwsync><file name="admin.html" server="wsa123.uits.indiana.edu//usr/local/apache/htdocs/mocks/" local="3288108944" remote="2639241274783540819" /><file name="centad.html" server="wsa123.uits.indiana.edu//usr/local/apache/htdocs/mocks/" local="3288190273" remote="2639241274783540819" /><file name="dept.html" server="wsa123.uits.indiana.edu//usr/local/apache/htdocs/mocks/" local="3288190273" remote="3246064628371138130" /><file name="maint.html" server="wsa123.uits.indiana.edu//usr/local/apache/htdocs/mocks/" local="3288711215" remote="2885605907461685514" /><file name="maint1.html" server="wsa123.uits.indiana.edu//usr/local/apache/htdocs/mocks/" local="3286464184" remote="2598728377286490028" /><file name="researcher1.html" server="wsa123.uits.indiana.edu//usr/local/apache/htdocs/mocks/" local="3286464185" remote="2598728377286490028" /><file name="researcher3.html" server="wsa123.uits.indiana.edu//usr/local/apache/htdocs/mocks/" local="3286464185" remote="2598728377286490028" /><file name="researcher4.html" server="wsa123.uits.indiana.edu//usr/local/apache/htdocs/mocks/" local="3286464185" remote="2598728377286490028" /><file name="researcher2.html" server="wsa123.uits.indiana.edu//usr/local/apache/htdocs/mocks/" local="3288108944" remote="3246064628371138130" /><file name="admin-batch-schedule.html" server="wsa123.uits.indiana.edu//usr/local/apache/htdocs/mocks/" local="3286464180" remote="2598553194160420775" /><file name="admin-EmployeeStatus.html" server="wsa123.uits.indiana.edu//usr/local/apache/htdocs/mocks/" local="3286464180" remote="2598553194160420775" /><file name="admin-EmployeeType.html" server="wsa123.uits.indiana.edu//usr/local/apache/htdocs/mocks/" local="3286464180" remote="2598553194160420775" /><file name="admin-MessageOfTheDay.html" server="wsa123.uits.indiana.edu//usr/local/apache/htdocs/mocks/" local="3286464180" remote="2598553194160420775" /><file name="admin-Parameter.html" server="wsa123.uits.indiana.edu//usr/local/apache/htdocs/mocks/" local="3286464180" remote="2598553194160420775" /><file name="admin-ParameterComponent.html" server="wsa123.uits.indiana.edu//usr/local/apache/htdocs/mocks/" local="3286464181" remote="2598553194160420775" /><file name="admin-ParameterModule.html" server="wsa123.uits.indiana.edu//usr/local/apache/htdocs/mocks/" local="3286464181" remote="2598553194160420775" /><file name="admin-ParameterType.html" server="wsa123.uits.indiana.edu//usr/local/apache/htdocs/mocks/" local="3286464181" remote="2598553194160420775" /><file name="admin-SystemOptions.html" server="wsa123.uits.indiana.edu//usr/local/apache/htdocs/mocks/" local="3286464181" remote="2598553194160420775" /><file name="admin-User.html" server="wsa123.uits.indiana.edu//usr/local/apache/htdocs/mocks/" local="3286464181" remote="2598553194160420775" /><file name="admin-wor-applicationconstants.html" server="wsa123.uits.indiana.edu//usr/local/apache/htdocs/mocks/" local="3286464181" remote="2598553194160420775" /><file name="admin-wor-documentoperation.html" server="wsa123.uits.indiana.edu//usr/local/apache/htdocs/mocks/" local="3286464181" remote="2598553194160420775" /><file name="admin-wor-documenttype.html" server="wsa123.uits.indiana.edu//usr/local/apache/htdocs/mocks/" local="3286464181" remote="2598553194160420776" /><file name="admin-wor-ruleattribute.html" server="wsa123.uits.indiana.edu//usr/local/apache/htdocs/mocks/" local="3286464181" remote="2598553194160420776" /><file name="admin-wor-ruletemplate.html" server="wsa123.uits.indiana.edu//usr/local/apache/htdocs/mocks/" local="3286464181" remote="2598553194160420776" /><file name="admin-wor-statisticsreport.html" server="wsa123.uits.indiana.edu//usr/local/apache/htdocs/mocks/" local="3286464181" remote="2598553194160420776" /><file name="admin-wor-workgrouptype.html" server="wsa123.uits.indiana.edu//usr/local/apache/htdocs/mocks/" local="3286464181" remote="2598553194160420776" /><file name="admin-wor-xmlingester.html" server="wsa123.uits.indiana.edu//usr/local/apache/htdocs/mocks/" local="3286464181" remote="2598553194160420776" /><file name="dept-award.html" server="wsa123.uits.indiana.edu//usr/local/apache/htdocs/mocks/" local="3286464182" remote="2598728377286490024" /><file name="dept-noaccess.html" server="wsa123.uits.indiana.edu//usr/local/apache/htdocs/mocks/" local="3286464182" remote="2598728377286490024" /><file name="dept-noaccess2.html" server="wsa123.uits.indiana.edu//usr/local/apache/htdocs/mocks/" local="3286464182" remote="2598728377286490024" /><file name="dept-organization-all.html" server="wsa123.uits.indiana.edu//usr/local/apache/htdocs/mocks/" local="3286962739" remote="376724847678134009" /><file name="dept-organization.html" server="wsa123.uits.indiana.edu//usr/local/apache/htdocs/mocks/" local="3286962738" remote="376724847678134009" /><file name="dept-propdev.html" server="wsa123.uits.indiana.edu//usr/local/apache/htdocs/mocks/" local="3286464182" remote="2598728377286490025" /><file name="dept-proplog.html" server="wsa123.uits.indiana.edu//usr/local/apache/htdocs/mocks/" local="3286464182" remote="2598728377286490025" /><file name="dept-sponsor-all.html" server="wsa123.uits.indiana.edu//usr/local/apache/htdocs/mocks/" local="3286464182" remote="2598728377286490025" /><file name="dept-sponsor.html" server="wsa123.uits.indiana.edu//usr/local/apache/htdocs/mocks/" local="3286464182" remote="2598728377286490025" /><file name="maint-misc-country.html" server="wsa123.uits.indiana.edu//usr/local/apache/htdocs/mocks/" local="3286464183" remote="2598728377286490025" /><file name="maint-misc-sponsortype.html" server="wsa123.uits.indiana.edu//usr/local/apache/htdocs/mocks/" local="3286464183" remote="2598728377286490025" /><file name="maint-misc-state.html" server="wsa123.uits.indiana.edu//usr/local/apache/htdocs/mocks/" local="3286464183" remote="2598728377286490025" /><file name="maint-pro-abstracttype.html" server="wsa123.uits.indiana.edu//usr/local/apache/htdocs/mocks/" local="3286464183" remote="2598728377286490025" /><file name="maint-pro-acttype.html" server="wsa123.uits.indiana.edu//usr/local/apache/htdocs/mocks/" local="3286962737" remote="376724847678134009" /><file name="maint-pro-carriertype.html" server="wsa123.uits.indiana.edu//usr/local/apache/htdocs/mocks/" local="3286464183" remote="2598728377286490026" /><file name="maint-pro-deadlinetype.html" server="wsa123.uits.indiana.edu//usr/local/apache/htdocs/mocks/" local="3286464183" remote="2598728377286490026" /><file name="maint-pro-degreetype.html" server="wsa123.uits.indiana.edu//usr/local/apache/htdocs/mocks/" local="3286464183" remote="2598728377286490026" /><file name="maint-pro-mailby.html" server="wsa123.uits.indiana.edu//usr/local/apache/htdocs/mocks/" local="3286464183" remote="2598728377286490026" /><file name="maint-pro-narrativestatus.html" server="wsa123.uits.indiana.edu//usr/local/apache/htdocs/mocks/" local="3286464183" remote="2598728377286490026" /><file name="maint-pro-narrativetype.html" server="wsa123.uits.indiana.edu//usr/local/apache/htdocs/mocks/" local="3286464183" remote="2598728377286490026" /><file name="maint-pro-PersonDocumentTypeCode.html" server="wsa123.uits.indiana.edu//usr/local/apache/htdocs/mocks/" local="3286464183" remote="2598728377286490026" /><file name="maint-pro-PersonTableEditableColumns.html" server="wsa123.uits.indiana.edu//usr/local/apache/htdocs/mocks/" local="3286464183" remote="2598728377286490026" /><file name="maint-pro-ProposalinResponse.html" server="wsa123.uits.indiana.edu//usr/local/apache/htdocs/mocks/" local="3286464183" remote="2598728377286490026" /><file name="maint-pro-RevisionType.html" server="wsa123.uits.indiana.edu//usr/local/apache/htdocs/mocks/" local="3286464183" remote="2598728377286490027" /><file name="maint-pro-ScienceKeyword.html" server="wsa123.uits.indiana.edu//usr/local/apache/htdocs/mocks/" local="3286464183" remote="2598728377286490027" /><file name="maint-pro-SubmissionType.html" server="wsa123.uits.indiana.edu//usr/local/apache/htdocs/mocks/" local="3286464184" remote="2598728377286490027" /><file name="maint-rulesquicklink.html" server="wsa123.uits.indiana.edu//usr/local/apache/htdocs/mocks/" local="3286464184" remote="2598728377286490027" /><file name="maint-shared-credittype.html" server="wsa123.uits.indiana.edu//usr/local/apache/htdocs/mocks/" local="3286464184" remote="2598728377286490027" /><file name="maint-shared-noticeofopportunity.html" server="wsa123.uits.indiana.edu//usr/local/apache/htdocs/mocks/" local="3286464184" remote="2598728377286490027" /><file name="maint-shared-nsfcode.html" server="wsa123.uits.indiana.edu//usr/local/apache/htdocs/mocks/" local="3286464184" remote="2598728377286490027" /><file name="maint-shared-proposaltype.html" server="wsa123.uits.indiana.edu//usr/local/apache/htdocs/mocks/" local="3286464184" remote="2598728377286490027" /><file name="maint-shared-questions.html" server="wsa123.uits.indiana.edu//usr/local/apache/htdocs/mocks/" local="3286464184" remote="2598728377286490027" /><file name="maint-shared-rolodex-all.html" server="wsa123.uits.indiana.edu//usr/local/apache/htdocs/mocks/" local="3286464184" remote="2598728377286490027" /><file name="maint-shared-rolodex.html" server="wsa123.uits.indiana.edu//usr/local/apache/htdocs/mocks/" local="3286464184" remote="2598728377286490027" /><file name="maint-shared-specialreview.html" server="wsa123.uits.indiana.edu//usr/local/apache/htdocs/mocks/" local="3286464184" remote="2598728377286490027" /><file name="maint-shared-specialreviewapprovaltype.html" server="wsa123.uits.indiana.edu//usr/local/apache/htdocs/mocks/" local="3286464184" remote="2598728377286490027" /><file name="maint-wor-preferences.html" server="wsa123.uits.indiana.edu//usr/local/apache/htdocs/mocks/" local="3286464184" remote="2598728377286490028" /><file name="maint-wor-routingreport.html" server="wsa123.uits.indiana.edu//usr/local/apache/htdocs/mocks/" local="3286464184" remote="2598728377286490028" /><file name="maint-wor-rules.html" server="wsa123.uits.indiana.edu//usr/local/apache/htdocs/mocks/" local="3286464184" remote="2598728377286490028" /><file name="maint-workgroup.html" server="wsa123.uits.indiana.edu//usr/local/apache/htdocs/mocks/" local="3286464184" remote="2598728377286490028" /><file name="researcher-prop-docsearh.html" server="wsa123.uits.indiana.edu//usr/local/apache/htdocs/mocks/" local="3286464185" remote="2598728377286490028" /><file name="researcher-propdev.html" server="wsa123.uits.indiana.edu//usr/local/apache/htdocs/mocks/" local="3286464185" remote="2598728377286490028" /><file name="maint-shared-instituterate.html" server="wsa123.uits.indiana.edu//usr/local/apache/htdocs/mocks/" local="3288709238" remote="2885605907461685514" /><file name="maint-pro-validce.html" server="wsa123.uits.indiana.edu//usr/local/apache/htdocs/mocks/" local="3288709238" remote="2885605907461685514" /><file name="maint-pro-validcalc.html" server="wsa123.uits.indiana.edu//usr/local/apache/htdocs/mocks/" local="3288709238" remote="2885605907461685515" /><file name="maint-pro-ratetype.html" server="wsa123.uits.indiana.edu//usr/local/apache/htdocs/mocks/" local="3288709238" remote="2885605907461685515" /><file name="maint-pro-rateclass.html" server="wsa123.uits.indiana.edu//usr/local/apache/htdocs/mocks/" local="3288709238" remote="2885605907461685515" /><file name="maint-pro-costelement.html" server="wsa123.uits.indiana.edu//usr/local/apache/htdocs/mocks/" local="3288709238" remote="2885605907461685515" /></dwsync>